{
 
  
    "users": [
       { "id":1 , "username":"" , "password": ""}
        
      ],
    "posts": [ 
      {"id": 1 , "post_title": "Independence", "post_body": " India got Independece on 15 August 1974", "authod_id":"123", "authod_username":"David" },
      {"id": 2 , "post_title": "Republic", "post_body": " India celebrates its republic day on 26 january", "authod_id":"1234", "authod_username":"M.D Das" }
       
      ],
    "comments": [ 
       { "id": 1, "author_id" :23, "author_name": "", "post_id":"", "comment_details": "" }
       ]
   
}